odoo/addons/pos_loyalty_exclude/README.rst
odoo/addons/pos_loyalty_exclude/__init__.py
odoo/addons/pos_loyalty_exclude/__manifest__.py
odoo/addons/pos_loyalty_exclude/i18n/it.po
odoo/addons/pos_loyalty_exclude/i18n/pos_loyalty_exclude.pot
odoo/addons/pos_loyalty_exclude/models/__init__.py
odoo/addons/pos_loyalty_exclude/models/loyalty_rule.py
odoo/addons/pos_loyalty_exclude/readme/CONTRIBUTORS.rst
odoo/addons/pos_loyalty_exclude/readme/DESCRIPTION.rst
odoo/addons/pos_loyalty_exclude/static/description/icon.png
odoo/addons/pos_loyalty_exclude/static/description/index.html
odoo/addons/pos_loyalty_exclude/static/src/tours/PosLoyaltyExcludeTour.esm.js
odoo/addons/pos_loyalty_exclude/tests/__init__.py
odoo/addons/pos_loyalty_exclude/tests/test_pos_loyalty_exclude.py
odoo_addon_pos_loyalty_exclude-16.0.1.0.1.dist-info/METADATA
odoo_addon_pos_loyalty_exclude-16.0.1.0.1.dist-info/WHEEL
odoo_addon_pos_loyalty_exclude-16.0.1.0.1.dist-info/top_level.txt
odoo_addon_pos_loyalty_exclude-16.0.1.0.1.dist-info/RECORD
