Metadata-Version: 2.1
Name: odoo-addon-pos_loyalty_exclude
Version: 16.0.1.0.1
Summary: Exclude products from sale loyalty program in POS
Home-page: https://github.com/OCA/pos
Author: Camptocamp, Odoo Community Association (OCA)
Author-email: support@odoo-community.org
License: AGPL-3
Classifier: Programming Language :: Python
Classifier: Framework :: Odoo
Classifier: Framework :: Odoo :: 16.0
Classifier: License :: OSI Approved :: GNU Affero General Public License v3
Requires-Python: >=3.10
Requires-Dist: odoo-addon-sale-loyalty-exclude<16.1dev,>=16.0dev
Requires-Dist: odoo<16.1dev,>=16.0a
